mcp_amadeus/__init__.py
mcp_amadeus/server.py
mcp_amadeus-0.0.2.dist-info/METADATA
mcp_amadeus-0.0.2.dist-info/WHEEL
mcp_amadeus-0.0.2.dist-info/entry_points.txt
mcp_amadeus-0.0.2.dist-info/top_level.txt
mcp_amadeus-0.0.2.dist-info/RECORD
