Metadata-Version: 2.4
Name: mcp-amadeus
Version: 0.0.2
Summary: MCP server for Amadeus integration
Project-URL: Homepage, https://github.com/yourusername/mcp-amadeus
Project-URL: Bug Tracker, https://github.com/yourusername/mcp-amadeus/issues
Requires-Python: >=3.10
Requires-Dist: mcp[cli]>=1.6.0
Requires-Dist: httpx>=0.24.0
